drf_simple_apikey/__init__.py
drf_simple_apikey/admin.py
drf_simple_apikey/apps.py
drf_simple_apikey/backends.py
drf_simple_apikey/crypto.py
drf_simple_apikey/models.py
drf_simple_apikey/mutli_api_crypto.py
drf_simple_apikey/parser.py
drf_simple_apikey/permissions.py
drf_simple_apikey/settings.py
drf_simple_apikey/utils.py
drf_simple_apikey/version.py
drf_simple_apikey/analytics/__init__.py
drf_simple_apikey/analytics/admin.py
drf_simple_apikey/analytics/apps.py
drf_simple_apikey/analytics/middleware.py
drf_simple_apikey/analytics/models.py
drf_simple_apikey/analytics/migrations/0001_initial.py
drf_simple_apikey/analytics/migrations/__init__.py
drf_simple_apikey/management/__init__.py
drf_simple_apikey/management/commands/__init__.py
drf_simple_apikey/management/commands/generate_fernet_key.py
drf_simple_apikey/management/commands/rotation.py
drf_simple_apikey/migrations/0001_initial.py
drf_simple_apikey/migrations/0002_alter_apikey_options.py
drf_simple_apikey/migrations/0003_alter_apikey_id.py
drf_simple_apikey/migrations/0003_apikey_blacklisted_ips_apikey_whitelisted_ips.py
drf_simple_apikey/migrations/__init__.py
drf_simple_apikey/rotation/__init__.py
drf_simple_apikey/rotation/admin.py
drf_simple_apikey/rotation/apps.py
drf_simple_apikey/rotation/models.py
drf_simple_apikey/rotation/utils.py
drf_simple_apikey/rotation/migrations/0001_initial.py
drf_simple_apikey/rotation/migrations/__init__.py
drf_simple_apikey-2.3.1.dist-info/licenses/LICENSE
drf_simple_apikey-2.3.1.dist-info/METADATA
drf_simple_apikey-2.3.1.dist-info/WHEEL
drf_simple_apikey-2.3.1.dist-info/top_level.txt
drf_simple_apikey-2.3.1.dist-info/RECORD
