Metadata-Version: 2.4
Name: drf-simple-apikey
Version: 2.3.1
Summary: API Key authentication and permissions for Django REST.
Home-page: https://github.com/koladev32/drf-simple-apikey
Author: Kolawole Mangabo
Author-email: onaelmangabo@gmail.com
License: MIT
Classifier: Development Status :: 5 - Production/Stable
Classifier: Intended Audience :: Developers
Classifier: License :: OSI Approved :: MIT License
Classifier: Operating System :: OS Independent
Classifier: Programming Language :: Python
Classifier: Programming Language :: Python :: 3.10
Classifier: Programming Language :: Python :: 3.11
Classifier: Programming Language :: Python :: 3.12
Classifier: Programming Language :: Python :: 3.13
Classifier: Programming Language :: Python :: Implementation :: PyPy
Classifier: Topic :: Software Development :: Libraries :: Python Modules
License-File: LICENSE
Requires-Dist: django<6.0,>=4.2.17
Requires-Dist: djangorestframework>=3.15.2
Requires-Dist: cryptography>=43.0.0
Provides-Extra: test
Requires-Dist: pytest; extra == "test"
Requires-Dist: coverage; extra == "test"
Requires-Dist: pytest-django; extra == "test"
Provides-Extra: tooling
Requires-Dist: black<25.0,>=24.0.0; extra == "tooling"
Requires-Dist: pylint; extra == "tooling"
Requires-Dist: bump2version; extra == "tooling"
Dynamic: license-file
